{"artist": "Yuk-cheung Chun feat. Misi Ke", "artisttranslit": "", "diff": "Medium", "diff_number": 7, "diffs": ["3555aaa670752d8c", "459c518ac8e8e3a1", "471ea74b6dc7ec79", "6fc39a18dd517925", "773d381b75ab2e41", "7fd4ae2e74ce3410", "d3239bbc35470216", "e69ff24a0b8a7bfb", "e9a716ce59f3ba42"], "hash": "d3239bbc35470216", "pack_name": "DigiMindAxel's original simfiles gamma style", "packs": ["DigiMindAxel's original simfiles gamma style"], "steps_type": "dance-single", "subtitle": "", "subtitletranslit": "", "title": "Electron", "titletranslit": ""}