{"hash":"2ffa2b16be777c3d","pack_name":"FnG ITG2 R21 Edit Tournament #2- 4-21-07","titletranslit":"","diff_number":12,"title":"Acid Over Sydney","directory":"(BeAsT1x5) Acid over Syndey","diff":"Hard","bpms":"0.000=120.000,4.000=122.000,8.000=124.000,12.000=127.000,16.000=130.000,20.000=132.000,24.000=135.000,28.000=138.000,32.000=140.000,36.000=141.000,40.000=142.000,44.000=144.000,48.000=145.000,52.000=146.000,56.000=146.500,64.000=147.000","subtitletranslit":"","steps_type":"dance-single","subtitle":"","artist":"blutonium boy (Steps By BeAsT1x5)","artisttranslit":""}