{"artist": "UZI-LAY", "artisttranslit": "", "diff": "Easy", "diff_number": 4, "diffs": ["0216d1d149011ea5", "384276d095e59ac0", "3bd90bf298fd4e5a", "3c1fe83a5952f83d", "4451a203538c744e", "78ef08a624c0f1a3", "b5233f246dfd5745", "be6d0919493dcb93", "c5c48814ed3f1901", "cfe6046962534ef3", "fc058606fbeffee5"], "hash": "cfe6046962534ef3", "pack_name": "Lugea", "packs": ["Lugea"], "steps_type": "dance-couple", "subtitle": "", "subtitletranslit": "", "title": "PUT YOUR FAITH IN ME (Jazzy) [Lugea]", "titletranslit": ""}