{"artist": "\u304b\u3081\u308a\u3042 feat. \u306a\u306a\u3072\u3089", "artisttranslit": "Camellia feat. Nanahira", "diff": "Easy", "diff_number": 6, "diffs": ["259bc61d54801240", "2807d274eb179155", "2fcd36c22113d6fd", "649742cf9a2328d2", "70d798038b9e9642", "b04781861eda4049", "b738b2d8e5701b76", "e71086f39e767be3", "f9d769a8f374686b"], "hash": "649742cf9a2328d2", "pack_name": "Z-I-v Summer Contest 2021", "packs": ["Z-I-v Summer Contest 2021", "forcednature's misc."], "steps_type": "dance-single", "subtitle": "", "subtitletranslit": "", "title": "\u30aa\u30ea\u30ac\u30df\u30ab\u30eb\u30fb\u30b9\u30a6\u30a3\u30fc\u30c8\u30e9\u30f4", "titletranslit": "Origamical sweet love"}