{"artist": "MSMcorp.", "artisttranslit": "", "diff": "Hard", "diff_number": 9, "diffs": ["062b0225992585bd", "15b7f9d4c04dc510", "58fbb8294b07bed1", "67b41fc52685811d", "7aab7fe3cd44f6c9", "881251d423ab22db", "89474858ffa7ab3f", "9fcd5d93ceb08aab", "c5f7a81b638b3501"], "hash": "062b0225992585bd", "pack_name": "Stepmania Revolutionary FIESTA", "packs": ["Stepmania Revolutionary FIESTA"], "steps_type": "dance-double", "subtitle": "", "subtitletranslit": "", "title": "Cloudiness", "titletranslit": ""}