{"artist": "kamome sano", "artisttranslit": "", "diff": "Hard", "diff_number": 10, "diffs": ["05b38b5cee024b27", "6f2ae181626be1b4", "769e5a97543b9dcf", "9552b7079bed0f9e", "f5a60809c1950ae7"], "hash": "05b38b5cee024b27", "pack_name": "Condor's Overly Cool & Kawaii Simfiles 01", "packs": ["Condor's Overly Cool & Kawaii Simfiles 01", "SDVX KAC 2012", "Tachyon Alfalfa Expansion 5"], "steps_type": "dance-single", "subtitle": "", "subtitletranslit": "", "title": "eclair au chocolat", "titletranslit": ""}