{"artist": "SUPER STAR \u6e80-MITSURU- vs. \u4f1d\u8aac\u306e\u30c0\u30f3\u30b5\u30fc \u30de\u30a4\u30af", "artisttranslit": "SUPER STAR MITSURU VS. Densetsu no dancer Mike", "diff": "Easy", "diff_number": 4, "diffs": ["33812af93c6931de", "4e30b1c92b5b2725", "50fa0d61aa95b3f6", "af7e414f903e7348", "b1c3eedf3aa262a5"], "hash": "b1c3eedf3aa262a5", "pack_name": "Skittles Steps Fo(u)rth (9ms)", "packs": ["Skittles Steps Fo(u)rth (9ms)"], "steps_type": "dance-single", "subtitle": "", "subtitletranslit": "", "title": "NO LIMIT -\u30aa\u30ec\u9054\u306b\u9650\u754c\u306f\u7121\u3044-", "titletranslit": "NO LIMIT -oretachi ni genkai wa nai-"}