{"artist": "Baby Alice", "artisttranslit": "", "diff": "Challenge", "diff_number": 11, "diffs": ["2979db5ff9523dc8", "69d36595ef8fd3c3", "72362f7a4c3fd925", "b1d75e70adc19adc", "fbf56da9aadf7329"], "hash": "b1d75e70adc19adc", "pack_name": "Ace Of Hearts Unstoppable Love Power(1)", "packs": ["Ace Of Arrows Vol. 08 - Deceived by Adoration", "Ace Of Hearts Pack", "Ace Of Hearts Unstoppable Love Power(1)"], "steps_type": "dance-single", "subtitle": "(Nightcore Mix)", "subtitletranslit": "", "title": "Pina Colada Boy", "titletranslit": ""}