{"artist": "\u30ea\u30c4\u30ab / By abokado", "artisttranslit": "Rituka / By abokado", "diff": "Challenge", "diff_number": 15, "diffs": ["1ea2c463cc2c0c6a", "526fa21580b58d65", "da1e0a72fff756e2"], "hash": "1ea2c463cc2c0c6a", "pack_name": "Secret Sister Complex Package", "packs": ["Secret Sister Complex Package"], "steps_type": "dance-single", "subtitle": "Halozy / Starry Presto", "subtitletranslit": "", "title": "\u30b7\u30fc\u30af\u30ec\u30c3\u30c8\u30b7\u30b9\u30bf\u30fc\u30b3\u30f3\u30d7\u30ec\u30c3\u30af\u30b9", "titletranslit": "Secret Sister Complex"}