{"artist": "Arctures", "artisttranslit": "", "diff": "Challenge", "diff_number": 12, "diffs": ["8726f032e7367173"], "hash": "8726f032e7367173", "pack_name": "All-American Sportscenter 4 (r3 final)", "packs": ["All-American Sportscenter 4 (r3 final)", "Fort Rapids V (12s-16s) r3 Final", "Fort Rapids VI (12s-18s) r2 final", "KOTC6", "Kings of the Coast 5", "Tachyon Beta", "Tachyon Series", "fort rapids vii", "rocky mount xi", "that pack", "universal tournament pack"], "steps_type": "dance-single", "subtitle": "", "subtitletranslit": "", "title": "Orange Sky", "titletranslit": ""}