{"title":"Drop The Bass Now","pack_name":"Systemic 2","bpms":"0.000=170.000,95.000=177.000,96.000=170.000,128.000=255.000,136.000=170.000,144.000=255.000,152.000=170.000,160.000=255.000,168.000=170.000,176.000=255.000,183.000=170.000,255.000=166.500,256.000=170.000,320.000=178.000,320.500=170.000","diff":"Hard","diff_number":9,"steps_type":"dance-single","hash":"c1a6ef81af66ff84","directory":"Drop The Bass Now (Hommarju Rmx)","artisttranslit":"","titletranslit":"","subtitletranslit":"","artist":"P*Light","subtitle":"(Hommarju Rmx)"}