{"artist": "Xi", "artisttranslit": "", "diff": "Challenge", "diff_number": 20, "diffs": ["750e8c31f52a9276"], "hash": "750e8c31f52a9276", "pack_name": "East Coast Stamina 4.5 Upper", "packs": ["ECS6 Qualifiers", "ECS7 Qualifiers", "East Coast Stamina 4.5", "East Coast Stamina 4.5 Upper", "East Coast Stamina 5", "East Coast Stamina 6 Qualifiers", "MWCSFA 3 - Pure Stamina (FA+)", "Tachyon Alfalfa Expansion 6"], "steps_type": "dance-single", "subtitle": "", "subtitletranslit": "", "title": "[20] FREEDOM DIVE", "titletranslit": ""}