{"artist": "\u6c34\u6a39\u5948\u3005", "artisttranslit": "", "diff": "Medium", "diff_number": 6, "diffs": ["448ccbafe1ebae8a", "61946f79e7e7f43c", "c02446cf7aafaa53"], "hash": "c02446cf7aafaa53", "pack_name": "Gochamaze Greatest Gigapack", "packs": ["Gochamaze Greatest Gigapack", "RARS", "RARSelection"], "steps_type": "dance-single", "subtitle": "\u30c6\u30a4\u30eb\u30ba\u30aa\u30d6\u30b7\u30f3\u30d5\u30a9\u30cb\u30a2 \u30c6\u30bb\u30a2\u30e9\u7de8/Gocha Pack", "subtitletranslit": "", "title": "\u5929\u7a7a\u306e\u30ab\u30ca\u30ea\u30a2", "titletranslit": "Tenkuu no Canaria"}