{"artist": "\u6c34\u6238\u3054\u5f53\u5730\u30a2\u30a4\u30c9\u30eb(\u4eee) \u3010\u8328\u57ce\u3011", "artisttranslit": "Mito Gotochi Idol (Kari) [Ibaraki]", "diff": "Easy", "diff_number": 4, "diffs": ["2945f7f8c2023db8", "5c36497e57bc454e", "6ef542ba2038e5df", "73c929c274df7059", "8a405429483b8581", "91c493d5cad13c39", "c03217783482a4e0"], "hash": "c03217783482a4e0", "pack_name": "DDR 2014 (for ITG)", "packs": ["DDR 2014 (for ITG)"], "steps_type": "dance-single", "subtitle": "", "subtitletranslit": "", "title": "MITO\u308c\u3066\uff01\u3044\u3070\u3089\u304d\u3063\u3057\u3085\u3060\uff5e\u308a\u3093", "titletranslit": "MITOrete! Ibarakisshuda~rin"}