{"artist": "JENNY ROM", "artisttranslit": "", "diff": "Medium", "diff_number": 6, "diffs": ["03cbf7a37f32150a", "3769b252784ad0ed", "5c4530990197f48f", "5fce8b7849304e94", "7371779a925a4ec4", "87463fa660dcdecb", "8ae09aeaa267b2d4", "a1857baee7bbc679", "a5c988878c121faf", "e3d17c113daddcda"], "hash": "a5c988878c121faf", "pack_name": "Misc DDR", "packs": ["DDR 1st Mix to EXTREME", "KoL DDR Post-5th & Pre-Supernova Edit Pack", "Misc DDR", "Shortysnmn2012 Originals"], "steps_type": "dance-single", "subtitle": "Speedy Mix", "subtitletranslit": "", "title": "SE\u00d1ORITA", "titletranslit": ""}