{"artist": "Camellia VS lapix", "artisttranslit": "", "diff": "Medium", "diff_number": 9, "diffs": ["34af12f4ba180ffc", "38c9125fdfdca62d", "3af7f47ff528aecc", "4858e7fa32318853", "5efa09e24cfb4f46", "64f2f60f67b5b831", "b3fcd9bd562fe7c7", "d9d97d0df6eb3427", "eb3f7f0f8349c150"], "hash": "eb3f7f0f8349c150", "pack_name": "DigiMindAxel's original simfiles gamma style", "packs": ["DigiMindAxel's original simfiles gamma style"], "steps_type": "dance-double", "subtitle": "", "subtitletranslit": "", "title": "Dead Music", "titletranslit": ""}