{"artist": "\u9e7f\u4e43", "artisttranslit": "Kano", "diff": "Hard", "diff_number": 8, "diffs": ["32ba880e0190b296", "3eda9168998ae3b4", "e9356fb01d516bf3", "eb597dc9fef484c3"], "hash": "eb597dc9fef484c3", "pack_name": "Jubo Impulsion [KB+PAD] (301-450)", "packs": ["Jubo Impulsion [KB+PAD] (301-450)"], "steps_type": "dance-single", "subtitle": "- \u306d\u3058\u5dfb\u304d\u7cbe\u970a\u6226\u8a18 \u5929\u93e1\u306e\u30a2\u30eb\u30c7\u30e9\u30df\u30f3 ED (2016)", "subtitletranslit": "- Nejimaki Seirei Senki Tenkyou no Alderamin ED (2016)", "title": "nameless", "titletranslit": ""}