{"artist": "Elissa", "artisttranslit": "", "diff": "Medium", "diff_number": 5, "diffs": ["1f39b3de3ba81ce7", "5e9e20e0f9291042", "a8992bd908ece04a", "d22daf2c660f23d9", "d260a45005aafcab", "e4ea85a2c69230b0", "eccb8cf03c0edd8a", "ed24241def8e4ede", "ff38b144616e87c9"], "hash": "a8992bd908ece04a", "pack_name": "All-American Sportscenter 4 (r3 final)", "packs": ["All-American Sportscenter 4 (r3 final)", "ITG Series", "In The Groove Rebirth 2"], "steps_type": "dance-single", "subtitle": "", "subtitletranslit": "", "title": "Mamboleo", "titletranslit": ""}