{"title":"Becoming Popular (The Pony Everypony Should Know)","diff_number":5,"directory":"Becoming Popular (The Pony Everypony Should Know) [8-bit]","diff":"Easy","hash":"b77114be7ab66cf6","subtitle":"(8-Bit Version)","subtitletranslit":"","pack_name":"TrotMania 1 - Rhythm is Magic","artist":"RainbowCrash88","titletranslit":"","artisttranslit":"","bpms":"0.000=120.000,154.000=94.000,158.000=92.000,169.500=86.000,170.000=82.000,172.000=70.000,174.000=60.000,175.000=45.000","steps_type":"dance-single"}