{"artist": "Togo Project feat.Sana", "artisttranslit": "", "diff": "Easy", "diff_number": 3, "diffs": ["054126f3f009c18c", "0592b761b1d0dc26", "44a69993eeb29e28", "5a8eced858d331f2", "95d7d0a413359837", "c123d6c8fcf88d29", "e3d1acba9dd94bb2"], "hash": "c123d6c8fcf88d29", "pack_name": "DDR EXTREME", "packs": ["DDR EXTREME", "DDR Extreme (for ITG)"], "steps_type": "dance-double", "subtitle": "", "subtitletranslit": "", "title": "Miracle Moon \uff5eL.E.D.LIGHT STYLE MIX\uff5e", "titletranslit": "Miracle Moon ~L.E.D.LIGHT STYLE MIX~"}