{"artist": "t+pazolite", "artisttranslit": "t+pazolite", "diff": "Challenge", "diff_number": 13, "diffs": ["272ac3b66668e5c0", "3072f76d5418df2d", "32428f17d385d3b4", "466357d59571e811", "57020fa657762d82", "8d5f3142d0cd570a", "9db95f313252186c", "a961212e4d7a4da5", "f224b2916c87f996"], "hash": "32428f17d385d3b4", "pack_name": "StepD-Mix Temple", "packs": ["StepD-Mix Temple"], "steps_type": "dance-single", "subtitle": "", "subtitletranslit": "", "title": "nekosogi Destruction", "titletranslit": "nekosogi Destruction"}