{"artist": "The Living Tombstone", "artisttranslit": "", "diff": "Easy", "diff_number": 6, "diffs": ["325db6242d4c60f7", "5dbe63c3e9443394", "7ecd2f6c37d6edec", "82809bdd411d8a19", "9bb693f1e71422ca", "a9f2b1756d8989b9", "b18f37b6b6340d01", "b65b2df00ed32f74", "be3425771a09a425"], "hash": "be3425771a09a425", "pack_name": "20%Cooler", "packs": ["20%Cooler", "TrotMania 1 - Rhythm is Magic", "Trotmania"], "steps_type": "dance-single", "subtitle": "", "subtitletranslit": "", "title": "Dubstep Dishwasher", "titletranslit": ""}