{"artist": "\u5bfa\u5cf6\u62d3\u7be4", "artisttranslit": "Terashima Takuma", "diff": "Easy", "diff_number": 3, "diffs": ["15b2e5c34b412fb0", "301586f583a6eb3f", "4548d63af67d8990", "df1d3b83daf223b2"], "hash": "4548d63af67d8990", "pack_name": "Jubo Cessation + 2019 [KB+PAD] (451-500)", "packs": ["Jubo Cessation + 2019 [KB+PAD] (451-500)"], "steps_type": "dance-single", "subtitle": "- \u8ee2\u751f\u3057\u305f\u3089\u30b9\u30e9\u30a4\u30e0\u3060\u3063\u305f\u4ef6 OP2 (2018)", "subtitletranslit": "- Tensei Shitara Slime Datta Ken OP2 (2018)", "title": "\u30e1\u30b0\u30eb\u30e2\u30ce", "titletranslit": "Meguru Mono"}