{"artist": "Joren \"Tensei\" De Bruin", "artisttranslit": "", "diff": "Beginner", "diff_number": 1, "diffs": ["01db2b4c5b4567cc", "25df47c13a14bcd2", "4f05eb268609c6db", "85532821467ac229", "c9218355fbe8789d"], "hash": "25df47c13a14bcd2", "pack_name": "Valex's Magical 4-Arrow Adventure 3", "packs": ["Valex's Magical 4-Arrow Adventure 3", "Valex's Magical 4-Arrow Adventure Series"], "steps_type": "dance-single", "subtitle": "", "subtitletranslit": "", "title": "Dance of Thorns", "titletranslit": ""}