{"artist": "SOUND HOLIC feat. Nana Takahashi", "artisttranslit": "", "diff": "Medium", "diff_number": 9, "diffs": ["2e2bdf4eb14cbc92", "9aa0b1f05464137c", "a62e34e1a3ab75bd", "aa8a218cfa7039fd", "aed5674ea30c1599", "caaf7cfb0775958b", "df031a889a5ebc22"], "hash": "aa8a218cfa7039fd", "pack_name": "forcednature's misc.", "packs": ["forcednature's misc."], "steps_type": "dance-single", "subtitle": "", "subtitletranslit": "", "title": "\u9e97 \uff5e\u3046\u3089\u3089\uff5e", "titletranslit": "Urara"}