{"artist": "\u304b\u3081\u308a\u3042", "artisttranslit": "Camellia", "diff": "Hard", "diff_number": 8, "diffs": ["1c45365fe7c3a901", "aa945e74ac6e1030", "c066f26593e1e15c", "dc3b830f310ee858", "e41d1626a895fd7a"], "hash": "aa945e74ac6e1030", "pack_name": "Skittles Steps Fo(u)rth (9ms)", "packs": ["Skittles Steps Fo(u)rth (9ms)"], "steps_type": "dance-single", "subtitle": "TS2 Redemption Finals - 2nd Place", "subtitletranslit": "", "title": "Treaty of Peace between GlitchHop and Moombahcore", "titletranslit": ""}