{"artist": "\u4e9c\u71b1\u5e2f\u30de\u30b8-SKA\u7206\u5f3e", "artisttranslit": "ANETTAI MAJI-SKA BAKUDAN", "diff": "Hard", "diff_number": 8, "diffs": ["5fb3c7d6fc97202c", "6cf024d594322bae", "78fcf7ca8b1e3d82", "890b68b1119e54cd", "9938a0bb5052ba3f", "aac6350f1c3f07e0", "ff5970c06b60de60"], "hash": "aac6350f1c3f07e0", "pack_name": "ddr classics", "packs": ["ddr classics"], "steps_type": "dance-double", "subtitle": "", "subtitletranslit": "", "title": "\u4e09\u6bdb\u732b\u30ed\u30c3\u30af", "titletranslit": "CALICO CAT ROCK"}