{"artist": "\u6298\u6238\u4f38\u6cbb with \u9ad8\u702c\u4e00\u4e5f Words by Key remixed dj p_server", "artisttranslit": "Shinji Orido with Kazuya Takase Words by Key remixed dj p_server", "diff": "Medium", "diff_number": 7, "diffs": ["246d46fad05a00c6", "3fef59a79054c072", "4800f6a6839548aa", "ca7c946cdf0d7df2", "f3fcb59769e829a6"], "hash": "4800f6a6839548aa", "pack_name": "Panzer Force Igselve", "packs": ["Panzer Force Igselve"], "steps_type": "dance-single", "subtitle": "-instrumental style-", "subtitletranslit": "", "title": "\u9ce5\u306e\u8a69", "titletranslit": "TORI NO UTA"}