{"artist": "Upon This Dawning", "artisttranslit": "", "diff": "Easy", "diff_number": 3, "diffs": ["092e1df02d1cded8", "163bd72c5f31d538", "190a119ea45b5604", "40eb04ac65b5eb79", "485f51c6abe47b7b", "5ccb0f7a22693174", "7d6ae76262223e18", "9084f0eb7b438851", "94e8c60b8d2a1000", "95f6b2e71d8eba58", "97ec50010093b635", "a23b4853c7ab2ad6", "af57c3ee3aebd3c4", "cda83489e07d4dfc", "df038848ecf9c835", "ec5cbdc657d04b1a"], "hash": "9084f0eb7b438851", "pack_name": "Encore Rebirth", "packs": ["Encore Rebirth", "R21Freak Pad File Comp VIII"], "steps_type": "dance-double", "subtitle": "", "subtitletranslit": "", "title": "Call Me Maybe", "titletranslit": ""}