{"artist": "dB soundworks", "artisttranslit": "", "diff": "Hard", "diff_number": 12, "diffs": ["2e811100ce4d19d3", "6e9097d3c36e3c1b", "977760812013e089", "a90a7adc107dd6da", "d7d68a00f2fbcdaa", "f03af91f129e2838"], "hash": "6e9097d3c36e3c1b", "pack_name": "Super Meat Boy! Full-Keyboard Stepmania Pack", "packs": ["Super Meat Boy! Full-Keyboard Stepmania Pack"], "steps_type": "dance-single", "subtitle": "Super Meat Boy! Soundtrack (2010)", "subtitletranslit": "", "title": "3-X Rocket Rider", "titletranslit": ""}