{"artist": "\u4f0a\u85e4\u771f\u6f84", "artisttranslit": "Masumi Itou", "diff": "Hard", "diff_number": 8, "diffs": ["cfd0a1e04c65ba41", "d854ef77c3be8ed0", "f3c6ceae56ff7456", "fcc02f012dd73760"], "hash": "fcc02f012dd73760", "pack_name": "ZIv Simfile Shuffle 2013", "packs": ["ZIv Simfile Shuffle 2013"], "steps_type": "dance-single", "subtitle": "", "subtitletranslit": "", "title": "\u30e6\u30e1\u306e\u306a\u304b\u30ce\u308f\u305f\u3057\u306e\u30e6\u30e1", "titletranslit": "Yume no Naka no Watashi no Yume"}