{"pack_name":"Jimbo's ITG2 R21 Edit Tournament #4- 6-28-08","titletranslit":"","directory":"(Ponchoz) Stratofortress","artist":"Stratovarius","hash":"8c979aaf87913f39","bpms":"0.000=180.000,7.000=359.999,8.000=180.020,11.000=359.999,12.000=180.040,16.000=359.999,19.000=178.000,20.000=180.000,276.000=360.000,284.000=183.000,289.500=360.000,294.500=183.000,301.500=360.000,338.500=180.000","title":"Stratofortress","subtitletranslit":"","diff_number":13,"diff":"Challenge","artisttranslit":"","subtitle":"","steps_type":"dance-single"}