{"artist": "\u4e03\u6761\u30ec\u30bf\u30b9\u30b0\u30eb\u30fc\u30d7 starring \u30b3\u30b3", "artisttranslit": "Lettuce Shichijou starring Koko", "diff": "Medium", "diff_number": 9, "diffs": ["061ab6fa7b0784e3", "092ab8f86dbab99f", "176ad177638f8661", "331fc9c937913100", "648c541e74e75051", "ad023bac703cf88e", "d911c8382f4d952d"], "hash": "331fc9c937913100", "pack_name": "forcednature's misc.", "packs": ["forcednature's misc."], "steps_type": "dance-double", "subtitle": "", "subtitletranslit": "", "title": "\u592a\u967d\u306f\u3084\u3081\u3066\uff01\u307c\u304f\u3089\u306e\u30b9\u30ab\u30fc\u30ec\u30c3\u30c8\u8b66\u5bdf", "titletranslit": "Taiyou wa yamete! Bokura no Scarlet keisatsu"}