{"artist": "Don't Hide the Background!", "artisttranslit": "", "diff": "Hard", "diff_number": 18, "diffs": ["3a4935b1bfb9fd2f", "6a131a08ee23b094", "73232e8f8888dbff", "7c6f1a905e2fc1ce", "b349ec5c6f06314e", "beac8d4f932c43e1", "f52604054e0111a6", "fe2107ae9b5f26c1", "fed00b2db8de8af9"], "hash": "3a4935b1bfb9fd2f", "pack_name": "Gym Intervals (Team BBC)", "packs": ["Gym Intervals (Team BBC)"], "steps_type": "dance-double", "subtitle": "", "subtitletranslit": "", "title": "90s Dance Megamix", "titletranslit": ""}