{"steps_type":"dance-single","bpms":"0.000=80.000,16.000=160.000,48.000=80.000,64.000=160.000,73.000=160.000,81.000=160.000,89.000=160.000,176.000=80.000,180.000=160.000,208.000=40.000,209.000=160.000,233.000=80.000,249.000=160.000,325.000=80.000","diff":"Challenge","pack_name":"Valex's Magical 4-Arrow Adventure","artisttranslit":"","subtitle":"","hash":"ca70c311feed1620","title":"Rawest Forest","diff_number":10,"directory":"Rawest Forest","artist":"Marta","subtitletranslit":"","titletranslit":""}