{"steps_type":"dance-single","hash":"d39dfa7448113e42","diff":"Challenge","bpms":"0.000=196.000,220.000=98.000,228.000=196.000,365.000=156.000,366.000=142.000,367.000=135.000,368.000=130.000,369.000=123.000,370.000=87.400,371.000=75.000","subtitle":"beatmania IIDX 22 PENDUAL","subtitletranslit":"Beatmania IIDX 22 Pendual","pack_name":"Otaku's Dream Mix 5 -Pad-","artisttranslit":"Nekomata L.E.D.Master+","directory":"Chrono Diver -PENDULUMs- (beatmania IIDX 22 PENDUAL) [Huzure]","diff_number":13,"title":"Chrono Diver -PENDULUMs-","artist":"猫叉L.E.D.Master+","titletranslit":"Chrono Diver -PENDULUMs-"}