{"bpms":"0.000=150.000,68.000=300.000,128.000=450.000,132.000=75.000,136.000=300.000,200.000=150.000,360.000=300.000,376.000=600.000,392.000=150.000,396.000=300.000","title":"The Underground","diff_number":7,"titletranslit":"","pack_name":"All in 1 GenreMix 2020 Part 1","subtitletranslit":"","diff":"Medium","directory":"Hardwell & Timmy Trumpet - The Underground","hash":"0efd7ac5ecb6afa0","steps_type":"dance-single","artist":"Hardwell & Timmy Trumpet","artisttranslit":"","subtitle":"- The Underground"}