{"artist": "Dr.Honda", "artisttranslit": "", "diff": "Hard", "diff_number": 10, "diffs": ["3c537dfb2dcf8a73", "5bbd28299ae9fbff", "a117e5b09979d61b", "b7b83dbbd8554d4a", "d424ff18c7b048b7", "f438dacad8513f89"], "hash": "f438dacad8513f89", "pack_name": "accelmix 4", "packs": ["DDR B3", "Valentine's Day", "accelmix 4"], "steps_type": "dance-single", "subtitle": "", "subtitletranslit": "", "title": "\u541b\u306e\u30cf\u30fc\u30c8\u306b\u30ed\u30c3\u30af\u30aa\u30f3", "titletranslit": "Kimi no Heart ni Lock-On"}