{"artist": "DJ Sharpnel remixed by GUHROOVY", "artisttranslit": "", "diff": "Challenge", "diff_number": 19, "diffs": ["1772992f12de5867", "2450213149247bdd", "4a48a4e9a63c3145", "6755685f4a547760", "6fe21938aa11ebdd", "72dc282b183f71f3"], "hash": "6fe21938aa11ebdd", "pack_name": "SHARPNELSTREAMZ Series", "packs": ["French Coast Stamina 2.5 Invitational", "Really Long Stuff", "SHARPNELSTREAMZ Series", "SHARPNELSTREAMZ v2"], "steps_type": "dance-single", "subtitle": "", "subtitletranslit": "", "title": "Sharpnel Sound Megamix 3", "titletranslit": ""}