{"artist": "Bill Hamel with Spacebar", "artisttranslit": "", "diff": "Easy", "diff_number": 3, "diffs": ["10a5f27308ab0140", "25444bcb9d05e38a", "3cf4d8398026c6ed", "58d2424496f3b9d8", "93d5affb89455fcc", "cefa5a43fcfa7966", "d320282017444da1", "fdd58174353d667a"], "hash": "cefa5a43fcfa7966", "pack_name": "DDR Xbox 360 Releases (for ITG)", "packs": ["DDR Xbox 360 Releases (for ITG)"], "steps_type": "dance-double", "subtitle": "", "subtitletranslit": "", "title": "Breathe The Air", "titletranslit": ""}