{"artist": "RevenG", "artisttranslit": "", "diff": "Easy", "diff_number": 5, "diffs": ["0c37cbaadf584b35", "349edb7e070e0f66", "5b74f8e879084142", "6a1c3f824607a346", "6fc8bfcefb7d26ae", "82ec2bf5577deb97", "bad1281a7218e4b6", "e9dfc23a90f15971", "f8a992561d7c1d69"], "hash": "f8a992561d7c1d69", "pack_name": "DDR Extreme (for ITG)", "packs": ["DDR EXTREME", "DDR Extreme (for ITG)"], "steps_type": "dance-double", "subtitle": "", "subtitletranslit": "", "title": "\u685c", "titletranslit": "SAKURA"}