{"artist": "t+pazolite", "artisttranslit": "", "diff": "Easy", "diff_number": 6, "diffs": ["31bee42ab3361109", "b421be4cfc7247c7", "e503f30e04216031", "f289c30904774ff5", "fc0dcbf53049e8b3"], "hash": "e503f30e04216031", "pack_name": "R21Freak And Aaronin.jp Individual Files Pre-2016", "packs": ["Braeden's Beats", "Braeden's Megapack v2", "R21Freak And Aaronin.jp Individual Files Pre-2016"], "steps_type": "dance-single", "subtitle": "", "subtitletranslit": "", "title": "Chipscape", "titletranslit": ""}