{"artist": "Y.W", "artisttranslit": "", "diff": "Medium", "diff_number": 5, "diffs": ["0818370318ac4aac", "0d917a53a6bb13ad", "606acbd2a4171264", "6a2b08ad1be1f1da", "76ecaa1ba66c4a34", "7741704876dcd825", "8549b25e00e7c729", "933aa4aa66f9df31", "d0659b95e7349390"], "hash": "6a2b08ad1be1f1da", "pack_name": "StepMania - YW MIX - Reworked", "packs": ["StepMania - YW MIX - Reworked"], "steps_type": "dance-double", "subtitle": "", "subtitletranslit": "", "title": "The white ground.", "titletranslit": ""}