{"artist": "DREAMS COME TRUE", "artisttranslit": "", "diff": "Easy", "diff_number": 2, "diffs": ["1bbbffa14aad81e2", "457db24762041c52", "52a2c3171a17f8c7", "85b56d5876a9816b", "a5bf05c9d26ac37e", "ac429595bd014b75", "b2e17054bef4731e", "c15582f1096eae42", "cd4603d69ab44cc6", "f955ef69e2741e1c"], "hash": "b2e17054bef4731e", "pack_name": "Dancing Stage Featuring Releases (for ITG)", "packs": ["Dancing Stage Featuring Releases (for ITG)"], "steps_type": "dance-couple", "subtitle": "", "subtitletranslit": "", "title": "SNOW DANCE", "titletranslit": ""}