{"artist": "\u00e4\u00b8\u0160\u00e7\u201d\u00b0\u00e6\u0153\u00b1\u00e9\u0178\u00b3", "artisttranslit": "", "diff": "Hard", "diff_number": 13, "diffs": ["4803d3befc97e005", "594c24d0766951d2", "ecc8c1d29e944f51"], "hash": "ecc8c1d29e944f51", "pack_name": "remi", "packs": ["remi"], "steps_type": "dance-single", "subtitle": "", "subtitletranslit": "", "title": "\u00e3\u0192\u2019\u00e3\u0192\u0178\u00e3\u0192\u201e\u00e3\u0192\u017d\u00e3\u0192\u0178\u00e3\u0192\u00a9\u00e3\u201a\u00a4", "titletranslit": ""}