{"artist": "ARM\uff0b\u5915\u91ce\u30e8\u30b7\u30df feat. miko", "artisttranslit": "ARM\uff0bYouno feat. miko", "diff": "Hard", "diff_number": 13, "diffs": ["09cdd6225b426c13", "20d9fab4db28eeec", "69e390b792774be6", "92d7984ce8e7a4ff", "bf0a4703921cd8ad", "d72d524643f678ed", "ddb77e794d9da60f", "de1c0b403a807806", "e3ca8f7ae38cdaa4"], "hash": "ddb77e794d9da60f", "pack_name": "DDR A", "packs": ["DDR A"], "steps_type": "dance-double", "subtitle": "", "subtitletranslit": "", "title": "\u30c1\u30eb\u30ce\u306e\u30d1\u30fc\u30d5\u30a7\u30af\u30c8\u3055\u3093\u3059\u3046\u6559\u5ba4", "titletranslit": "Cirno's Perfect Math Class"}