{"artist": "Eurobeat Brony", "artisttranslit": "", "diff": "Challenge", "diff_number": 15, "diffs": ["0892adf2a2650856", "3315920f05349333", "480beb34c92838d6", "5d95175a3ea03206", "7a6b6c4b674f87bc", "90226e3887f75ad3", "c2382a88200952e4", "f905f18ec9f900f1"], "hash": "5d95175a3ea03206", "pack_name": "TrotMania 5 - Shrive", "packs": ["TrotMania 5 - Shrive"], "steps_type": "dance-single", "subtitle": "(Parasprite Remix)", "subtitletranslit": "", "title": "Giggle at the Ghostie", "titletranslit": ""}