{"artist": "When Machines Dream", "artisttranslit": "", "diff": "Easy", "diff_number": 4, "diffs": ["035fc01c63b64c93", "3c0b457db66dde42", "5ee3adb3e161cc1e", "62b0ee26ca726f3f", "653e473471e027c8", "72da3343eca25cc3", "8c9c264783f49cf9", "991423a0e4d2edc6", "d9d77d4cf709cf75"], "hash": "653e473471e027c8", "pack_name": "In The Groove Rebirth 2", "packs": ["DDR Illini Tournament Pack - Rebirth 2 [01-2012]", "ITG Series", "In The Groove Rebirth 2"], "steps_type": "dance-single", "subtitle": "", "subtitletranslit": "", "title": "End of Line", "titletranslit": ""}