{"artist": "\u78a7\u967d\u5b66\u5712\u751f\u5f92\u4f1a", "artisttranslit": "heiyougakuen seitokai", "diff": "Challenge", "diff_number": 12, "diffs": ["65ff048311ffe418", "732a8bced9bf5b8f", "7b15f077dfde7c44", "845e4c802f2bd0e8", "991516c910ab9992", "e6b9bc5a943d8d60"], "hash": "65ff048311ffe418", "pack_name": "nm", "packs": ["nm"], "steps_type": "dance-single", "subtitle": "\u751f\u5f92\u4f1a\u306e\u4e00\u5b58 ED", "subtitletranslit": "seitokai no ichizon ED   ", "title": "\u4e0a\u4e0a\u4e0b\u4e0b\u5de6\u53f3\u5de6\u53f3BA", "titletranslit": "ueue shitashita hidarimigihidarimigi BA"}