{"artist": "ave new feat.\u4f50\u5009\u7d17\u7e54", "artisttranslit": "ave new feat. Saori Sakura", "diff": "Easy", "diff_number": 5, "diffs": ["26eb6131ab2b0900", "31dd98517bf3986d", "dee4dfb383185a40"], "hash": "26eb6131ab2b0900", "pack_name": "U.K.U.G. Simfiles 25-50", "packs": ["U.K.U.G", "U.K.U.G. Simfiles 25-50"], "steps_type": "dance-single", "subtitle": "\u30d5\u30a9\u30bb\u30c3\u30c8 -Cafe au Le Ciel Bleu-", "subtitletranslit": "Fossette -Cafe au Le Ciel Bleu- ", "title": "Vanille Rouge", "titletranslit": "Vanille Rouge"}