{"artist": "BEMANI Sound Team \"L.E.D.\" feat. KOTOKO", "artisttranslit": "L.E.D. feat. KOTOKO", "diff": "Medium", "diff_number": 14, "diffs": ["1c71eb2969e6b20b", "4969d8ed0df42fb9", "53f44b1b80f83e61", "5f032ab5d5b4e6ab", "92fdd5cc1038f1c6", "a053b01550e6233a", "b0254dc1444f147f", "d56f29b14c2a7571", "ffe089c0e2838990"], "hash": "92fdd5cc1038f1c6", "pack_name": "forcednature's misc.", "packs": ["forcednature's misc."], "steps_type": "dance-single", "subtitle": "", "subtitletranslit": "", "title": "UNDERWORLD HOLOGRAPHY", "titletranslit": ""}