{"artist": "kors k", "artisttranslit": "", "diff": "Challenge", "diff_number": 15, "diffs": ["0d6db84db191da55", "389bcb2be5680cc4", "5b4457be28d16d35", "687da00d6303b819", "87d9257b15394961", "974795d67afd0bc5", "97e58926326318c6", "ada9718efc518801", "cc4732eb507b34a8"], "hash": "cc4732eb507b34a8", "pack_name": "DigiMindAxel's original simfiles gamma style", "packs": ["DigiMindAxel's original simfiles gamma style"], "steps_type": "dance-single", "subtitle": "", "subtitletranslit": "", "title": "Hatcha Metcha Party", "titletranslit": ""}