{"artist": "Onyx", "artisttranslit": "", "diff": "Challenge", "diff_number": 13, "diffs": ["32bf320d964b8e79", "5b7ca151813ed7fe", "7837f21a4b27dfc7", "8f492816c59f4281", "ac2fa97de15f6890", "b50e2dd66d62e7a5", "c27e022110ef2150", "d27ca3edc3a8499f", "e0e2db926c60f995"], "hash": "d27ca3edc3a8499f", "pack_name": "Broadway Blast 4", "packs": ["BlueChaos Simfiles - The Complete Box Set", "Broadway Blast 4"], "steps_type": "dance-single", "subtitle": "", "subtitletranslit": "", "title": "Hasse Mich", "titletranslit": ""}