{"artist": "Orange Lounge", "artisttranslit": "", "diff": "Challenge", "diff_number": 8, "diffs": ["19e8a2b06f2ba949", "2c8ad550aea9185e", "4c4ebf762007ddf8", "562582dd79377894", "5fed1eec0a6e825a", "7c2c82b36f6a161b", "bc5ad6337e859efa", "d2b7be70b193f0db", "dd31a9cf0606686d", "f3b1deee57f622ca", "fc004383d52cf174"], "hash": "d2b7be70b193f0db", "pack_name": "ddr ps2 us", "packs": ["Dominator's Edits", "ddr ps2 us"], "steps_type": "dance-double", "subtitle": "", "subtitletranslit": "", "title": "LOVE IS ORANGE", "titletranslit": ""}