{"artist": "\u30a2\u30eb\u30df\u30d3\u30b8\u30e7\u30f3", "artisttranslit": "Alumivision", "diff": "Challenge", "diff_number": 15, "diffs": ["16614fd71d3603cb", "36c55c47fa0364f3", "50152dc2abd28955", "71b08d5ce481209f", "73dd3b0febcf4317", "98dbaeeb6250061a", "a21fdacbbaa84ae4"], "hash": "71b08d5ce481209f", "pack_name": "Boundary", "packs": ["Boundary"], "steps_type": "dance-single", "subtitle": "", "subtitletranslit": "", "title": "\u8907\u5c48\u6298\u6027\u5bfe\u6607\u83ef\u9632\u8b77\u819c", "titletranslit": "Dual Reflective Anti-Sublimation Film"}