{"artist": "\u65e5\u5411\u7f8e\u30d3\u30bf\u30fc\u30b9\u30a4\u30fc\u30c4\u266a", "artisttranslit": "Hinatabi Bitter Sweets\u266a", "diff": "Hard", "diff_number": 7, "diffs": ["3fe12f2d48da9080", "77dd2e33684cec44", "930a21a70a398b05", "9bebbfe5fbd72581", "b340108e3bda1abb", "baf16543c6ca802e", "dd76715be56cdbad", "ddcf830e9ee33109", "eab9c84ceddc4fac"], "hash": "baf16543c6ca802e", "pack_name": "DDR 2014 (for ITG)", "packs": ["DDR 2014 (for ITG)"], "steps_type": "dance-single", "subtitle": "", "subtitletranslit": "", "title": "neko*neko", "titletranslit": ""}