{"artist": "fh\u00e1na", "artisttranslit": "", "diff": "Medium", "diff_number": 6, "diffs": ["5e00a2bce3ec91ec", "95d38444c3008d8c", "b622f876d5f87083", "d48abb8ce530bd8a", "e23a73fe9a4db15b"], "hash": "d48abb8ce530bd8a", "pack_name": "Huzure's Simfiles 301-325", "packs": ["Huzure's Simfiles 301-325"], "steps_type": "dance-single", "subtitle": "\u30b3\u30e1\u30c3\u30c8\u30fb\u30eb\u30b7\u30d5\u30a1\u30fc", "subtitletranslit": "Comet Lucifer", "title": "\u30b3\u30e1\u30c3\u30c8\u30eb\u30b7\u30d5\u30a1\u30fc ~The Seed and the Sower~", "titletranslit": "Comet Lucifer ~The Seed and the Sower~"}