{"artist": "Upon This Dawning", "artisttranslit": "", "diff": "Easy", "diff_number": 4, "diffs": ["092e1df02d1cded8", "40eb04ac65b5eb79", "485f51c6abe47b7b", "7d6ae76262223e18", "9084f0eb7b438851", "95f6b2e71d8eba58", "97ec50010093b635", "af57c3ee3aebd3c4", "ec5cbdc657d04b1a"], "hash": "092e1df02d1cded8", "pack_name": "R21Freak Pad File Comp VIII", "packs": ["R21Freak Pad File Comp VIII"], "steps_type": "dance-single", "subtitle": "", "subtitletranslit": "", "title": "Call Me Maybe", "titletranslit": ""}