{"artist": "Crusher-P", "artisttranslit": "", "diff": "Challenge", "diff_number": 9, "diffs": ["0d8c37cdb0b7d0f6", "3b3b6c64ee466288", "41a5b2d104fc7fe9", "85f81847cffbc9d8", "8dd332fb94ccd825"], "hash": "0d8c37cdb0b7d0f6", "pack_name": "Girlpocalypse 2023 - Timing", "packs": ["5guys1pack", "ECFA 2019 - Middle", "ECFA 2021 (09s DLC)", "Girlpocalypse 2023 - Timing"], "steps_type": "dance-single", "subtitle": "(The Living Tombstone Remix)", "subtitletranslit": "", "title": "[09, Lv1] ECHO", "titletranslit": ""}