{"artist": "Sonic Adventure 1 Theme", "artisttranslit": "", "diff": "Hard", "diff_number": 9, "diffs": ["04bbc6ecb4f9cb60", "18656f8beb1dbd87", "2c0fe9109a811485", "45af8013c2432ace", "b2c99b7da5853b4e", "c45825d9bdb7d415", "d4223d0c25bce002", "e76c111a31b4a15a"], "hash": "2c0fe9109a811485", "pack_name": "DDRExtreme.co.uk presents VideoGames Mix 2005", "packs": ["DDRExtreme.co.uk presents VideoGames Mix 2005", "dancefreak"], "steps_type": "dance-double", "subtitle": "", "subtitletranslit": "", "title": "Open Your Heart", "titletranslit": ""}