{"artist": "BoA", "artisttranslit": "", "diff": "Medium", "diff_number": 5, "diffs": ["58a7df7852704f31", "6ed99ca2ff7574b7", "8a00bf099c51ef13", "ab7179f13fdd167b", "c8af182581fa172d"], "hash": "c8af182581fa172d", "pack_name": "Jubo New Era [KB+PAD] (151-300)", "packs": ["Jubo New Era [KB+PAD] (151-300)"], "steps_type": "dance-single", "subtitle": "- \u30d5\u30a7\u30a2\u30ea\u30fc\u30c6\u30a4\u30eb2 OP1/OP15 (2014)", "subtitletranslit": "- Fairy Tail 2 OP1/OP15 (2014)", "title": "Masayume Chasing", "titletranslit": ""}