{"artist": "kors k", "artisttranslit": "", "diff": "Easy", "diff_number": 3, "diffs": ["318293b41d76a70f", "3776c1e568d98a5b", "4536d0de822d1465", "521bec740faae70a", "70f38c052a232881", "83e1793e058cd506", "c10da0db45603932", "cb8e6eba564143c7", "eb8e847f36b1e0ef"], "hash": "318293b41d76a70f", "pack_name": "ZIv's Summer Contest 2012", "packs": ["Silverhawke's pack 02", "ZIv's Summer Contest 2012"], "steps_type": "dance-single", "subtitle": "", "subtitletranslit": "", "title": "Kailua", "titletranslit": ""}