{"artist": "NAOKI feat.YUKI", "artisttranslit": "", "diff": "Medium", "diff_number": 5, "diffs": ["197651cf819430cf", "223961b17438683b", "2cbd44905fa53e90", "5e4a0b174c617bec", "5e7a0b6c17518a27", "640822cefeb19361", "82b59b73f6cc2381", "aa36aede691c4c9f", "ed0dfafaaab898c5"], "hash": "ed0dfafaaab898c5", "pack_name": "KoL DDR Post-5th & Pre-Supernova Edit Pack", "packs": ["KoL DDR Post-5th & Pre-Supernova Edit Pack"], "steps_type": "dance-double", "subtitle": "", "subtitletranslit": "", "title": "\u84bc\u3044\u885d\u52d5(for EXTREME)", "titletranslit": "AOI SHOUDOU(for EXTREME)"}