{"diff":"Easy","pack_name":"Vocaloid Collaboration 5","artist":"黒髪ストロングP feat. 鏡音リン","title":"DOGS","bpms":"0.000=112.000,20.000=112.009,21.000=112.000,22.000=111.995,23.000=112.000,41.000=112.009,42.000=112.000,44.000=111.995,45.000=112.000,83.000=112.005,84.000=112.000,88.000=111.995,89.000=112.000","directory":"[mirelle] Kagamine Rin - DOGS","subtitletranslit":"","steps_type":"dance-single","diff_number":4,"artisttranslit":"Kagamine Rin","titletranslit":"","subtitle":"VCP 5","hash":"a151a27a3d7c3ec3"}