{"artist": "SOUND HOLIC feat. Nana Takahashi", "artisttranslit": "", "diff": "Hard", "diff_number": 3, "diffs": ["28846c21e3bec623", "bd5da551edeb19f9"], "hash": "28846c21e3bec623", "pack_name": "Gochamaze Greatest Gigapack 2", "packs": ["Gochamaze Greatest Gigapack 2"], "steps_type": "dance-single", "subtitle": "\u4ea1\u304d\u738b\u5973\u306e\u70ba\u306e\u30bb\u30d7\u30c6\u30c3\u30c8 \u30c4\u30a7\u30da\u30b7\u30e5\u306e\u5e7c\u304d\u672b\u88d4/Gocha Pack2", "subtitletranslit": "", "title": "Pri\u00e8re", "titletranslit": "Priere"}