{"artist": "Some asian guy", "artisttranslit": "", "diff": "Challenge", "diff_number": 12, "diffs": ["1b3e074ebeffa446", "2a3f4e2121245a2f", "3e639a5fb2c62a43", "931669f40d8de30b", "d84f879c9cba75c7"], "hash": "3e639a5fb2c62a43", "pack_name": "All-American Sportscenter 4 (r3 final)", "packs": ["All-American Sportscenter 4 (r3 final)", "DDR Illini Tournament Expansion v5 [01-2012]", "Doubles Tournament Expansion R3 (All Charts)", "Fort Rapids VI (12s-18s) r2 final", "GIRLS", "GIRLS Invitational Tournament", "KOTC6", "Kings of the Coast 5", "Tachyon Alfalfa Expansion 2", "Tachyon Gamma", "Tachyon Series", "fort rapids vii", "intel western stamina and speed", "rocky mount xi", "that pack"], "steps_type": "dance-single", "subtitle": "", "subtitletranslit": "", "title": "Tougen", "titletranslit": ""}