{"artist": "MiTis feat. Crywolf", "artisttranslit": "", "diff": "Easy", "diff_number": 3, "diffs": ["09b6bbc9ffeb39f7", "0fbd3d49b1ccfd23", "1e52bdf87f883431", "34ffcd9b8c5b9749", "3eb67f7dc9c74d59", "44c9934c6f79b150", "783022eb7c0ecd26", "7b5b627abb406e11", "eb898c7714b4ef81", "f4475b64698a8566"], "hash": "3eb67f7dc9c74d59", "pack_name": "Simply Momo Episode 1 (+0.009)", "packs": ["Simply Momo Episode 1 (+0.009)"], "steps_type": "dance-single", "subtitle": "(Vocal Mix)", "subtitletranslit": "", "title": "Oasis", "titletranslit": ""}