{"artist": "DongBang", "artisttranslit": "", "diff": "Challenge", "diff_number": 15, "diffs": ["59ebe667c38e98db"], "hash": "59ebe667c38e98db", "pack_name": "Koosoray", "packs": ["Koosoray"], "steps_type": "dance-single", "subtitle": "-\u00aa\u00c9\u00aa\u00ad\u00aa\u00c9\u00aa\u00ad\u00a3\u00a1\u00aa\u00d1\u00aa\u00a1\u00aa\u00c6\u00aa\u00a3\u00aa\u00df\u00aa\u00c3\u00aa\u00af\u00aa\u00b9-", "subtitletranslit": "", "title": "\u00e6\u00c7\u00aa\u00ce\u00aa\u00b4\u00aa\u00a9\u00aa\u00b9\u00aa\u00c8\u00a1\u00d9\u00aa\u00a2\u00aa\u00f3\u00aa\u00b5\u00aa\u00f3\u00aa\u00d6\u00aa\u00eb", "titletranslit": ""}