{"artist": "BEMANI Sound Team \"Darker Vs. JUSTICE\"", "artisttranslit": "BEMANI Sound Team \"Darker Vs. JUSTICE\"", "diff": "Beginner", "diff_number": 10, "diffs": ["228815f09e00ea57", "470d6a582af489b8", "7642b2c5f08d46be", "9fba0898e93a30a8", "c0ec47d03daa4063", "d29451c7e1ec866b", "d3cfef30f6c67bec"], "hash": "228815f09e00ea57", "pack_name": "FEARMIX 2023", "packs": ["FEARMIX 2023"], "steps_type": "dance-single", "subtitle": "", "subtitletranslit": "", "title": "V\u00d8ID", "titletranslit": ""}