{"artist": "\u7d50\u8863(CV\uff1a\u9ad8\u7530\u6182\u5e0c)", "artisttranslit": "Yui(CV.Yuuki Takada)", "diff": "Medium", "diff_number": 14, "diffs": ["004e4896e8b1cbed", "05352d055c49111a", "3a7e0b29bcf35543", "78a4477a54816172"], "hash": "78a4477a54816172", "pack_name": "Acerola", "packs": ["Acerola"], "steps_type": "dance-single", "subtitle": "\u4e09\u30c4\u661f\u30ab\u30e9\u30fc\u30ba (2018)", "subtitletranslit": "Mitsuboshi Colors (2018)", "title": "\u308f\u305f\u3057\u306eCOLOR(S)", "titletranslit": "Watashi no COLOR(S)"}