{"artist": "\u30eb\u30bc", "artisttranslit": "Luze", "diff": "Challenge", "diff_number": 18, "diffs": ["14f6622c8706391a", "1f5c2db6339c05c7", "4498352759e2cbbc", "9377fb52250687a2", "9a90dc9d69ad38f0", "adfa19a5b5e8b5df", "d01005fc80c1c787", "ed5c9a608dc983d4", "f7c5f5daba66abbe"], "hash": "f7c5f5daba66abbe", "pack_name": "NTR Squad StepDDR Simfiles", "packs": ["NTR Squad StepDDR Simfiles"], "steps_type": "dance-double", "subtitle": "", "subtitletranslit": "", "title": "\u30a8\u30fc\u30bf\u30fb\u30d9\u30fc\u30bf\u30fb\u30a4\u30fc\u30bf", "titletranslit": "Eta Beta Eta"}