{"titletranslit":"LAMENT ~Yagate Yorokobi wo~","subtitle":"- 伝説の勇者の伝説 Opening","steps_type":"dance-single","subtitletranslit":"- The Legend of the Legendary Heroes Opening","directory":"[Huzure] LAMENT ~Yagate Yorokobi wo~ [The Legend of the Legendary Heroes Opening]","diff":"Medium","hash":"770a93fb4a471b8f","artist":"結城アイラ","diff_number":6,"artisttranslit":"Yuuki Aira","title":"LAMENT ~やがて喜びを~","bpms":"0.000=139.000,30.000=69.500,32.000=139.000,96.000=69.500,108.000=139.000","pack_name":"Huzure's 61-90 Simfiles"}