{"artist": "Icky", "artisttranslit": "", "diff": "Hard", "diff_number": 9, "diffs": ["31860eb11cbf299f", "70ad43f1b98c6d08", "7b552d270b270693", "80047f797992731d", "917f07230882f992", "ae002914583decc9", "b3013274003c369a", "ea5915b4ab4633af", "f67f79feea551a9f"], "hash": "ea5915b4ab4633af", "pack_name": "Arrows are Magic Vol. 2", "packs": ["Arrows are Magic Vol. 2"], "steps_type": "dance-double", "subtitle": "", "subtitletranslit": "", "title": "Interrobang Pie Invades Equestria", "titletranslit": ""}