{"artist": "Billy Idol", "artisttranslit": "", "diff": "Challenge", "diff_number": 9, "diffs": ["105558804053997e", "49c48e21e7701e7f", "6adbae09527f18b5", "8163c0d39651cb40", "9cc4e64b29ad5836", "c363c0f2b2513e2e", "cccf7775bf3a29c1", "e16b1210ab5a00ec", "fad21b813ed27a77"], "hash": "105558804053997e", "pack_name": "80s Greatest Hits Volume 1", "packs": ["80s Greatest Hits Volume 1"], "steps_type": "dance-double", "subtitle": "", "subtitletranslit": "", "title": "Rebel Yell", "titletranslit": ""}