{"artist": "dj TAKA meets DJ YOSHITAKA", "artisttranslit": "", "diff": "Challenge", "diff_number": 16, "diffs": ["0fbb3453e890d049", "74961375a600ab26", "a1f65177e158e648"], "hash": "0fbb3453e890d049", "pack_name": "East Coast Stamina 4.5", "packs": ["Cirque Series", "Cirque du Zonda", "ECS7 Qualifiers", "East Coast Stamina 4.5", "East Coast Stamina 4.5 Upper", "Tachyon Alfalfa"], "steps_type": "dance-single", "subtitle": "", "subtitletranslit": "", "title": "[16] Elemental Creation", "titletranslit": ""}