{"artist": "Reflection Theory", "artisttranslit": "", "diff": "Medium", "diff_number": 4, "diffs": ["13a98263c3dd79e2", "1f0aab8c2a79ed01", "986220b970097506", "a4fa6b73f4023eb5", "a4fd3e91f992a574", "aaa73f3973655129", "c007f0167ae0c219", "c051a8b20482db4b", "ebb648ff403ff16b", "ece994f2cd7d1589", "fb13f60adbe6e8c2"], "hash": "a4fa6b73f4023eb5", "pack_name": "In The Groove", "packs": ["In The Groove"], "steps_type": "dance-single", "subtitle": "", "subtitletranslit": "", "title": "Don't Promise Me", "titletranslit": ""}