{"artist": "EGOIST", "artisttranslit": "", "diff": "Hard", "diff_number": 12, "diffs": ["1bc24e1d21b7fc79", "3455ffe801dbfce8", "c1bf4b19c5793f7c"], "hash": "3455ffe801dbfce8", "pack_name": "Solo Japan & Rulz Pack 3", "packs": ["Gundam-Dude Solo Simfiles I", "Solo Japan & Rulz Pack 3"], "steps_type": "dance-solo", "subtitle": "Psycho-Pass (2012)", "subtitletranslit": "", "title": "\u540d\u524d\u306e\u306a\u3044\u602a\u7269 (TV Edit 92s ver)", "titletranslit": "Namae no Nai Kaibutsu (TV Edit 92s ver)"}