{"artist": "JOGA", "artisttranslit": "", "diff": "Hard", "diff_number": 8, "diffs": ["010cf2f2be42ecef", "3d4d4e1c513b5427", "59997513313e6b91", "5e2e2788047379e1", "6c13164983cc2c9a", "7bf1d83b3d9199c1", "86d5065551761c53", "9f8574cc462fe095", "a892ccb26f1b2aa3", "dadce35af994915e", "e2ac09ca90a9798d"], "hash": "9f8574cc462fe095", "pack_name": "DDR 4thMIX AC JP", "packs": ["DDR 4th Mix (for ITG)", "DDR 4thMIX AC JP"], "steps_type": "dance-double", "subtitle": "", "subtitletranslit": "", "title": "DAM DARIRAM (KCP MIX)", "titletranslit": ""}