{"artist": "EasyPop feat. \u5b9f\u8c37\u306a\u306a&\u9e7f\u4e43", "artisttranslit": "EasyPop feat. Nana Mitani & Kano", "diff": "Medium", "diff_number": 7, "diffs": ["1f923cbdd660065a", "21faf907420db6ee", "541a4d13b9879bd7", "69d0c32662bb84e9", "fd6f5fe80ba11ff8"], "hash": "fd6f5fe80ba11ff8", "pack_name": "xythar presents a bunch of files in various states of completion (with arrows)", "packs": ["Xythar presents A Bunch Of Files In Various States Of Completion (With Arrows)", "xythar presents a bunch of files in various states of completion (with arrows)"], "steps_type": "dance-single", "subtitle": "(2011 vocal cover)", "subtitletranslit": "", "title": "Happy Synthesizer", "titletranslit": ""}