{"artist": "Blackbeat", "artisttranslit": "Blackbeat", "diff": "Easy", "diff_number": 4, "diffs": ["1f057bf0da848262", "40ce9bed89259f9e", "890c23af99eb4378", "a1f44af2e97fae43", "bcab1a3f81a11386", "c2927827709d5e4c", "d6012e6759d81925"], "hash": "40ce9bed89259f9e", "pack_name": "TDR-Mix^3 -Original Edition-", "packs": ["TDR-Mix^3 -Original Edition-"], "steps_type": "dance-double", "subtitle": "", "subtitletranslit": "", "title": "Breakbeats earthquake", "titletranslit": "Breakbeats earthquake"}