{"artist": "C2C", "artisttranslit": "", "diff": "Challenge", "diff_number": 10, "diffs": ["13bab7b1c9b5a1aa", "2f28ee533371d123", "5e831990920c7b4d", "c2abe1df283ce3d4", "c836b3acbd503b54", "cad006179c2b5513"], "hash": "2f28ee533371d123", "pack_name": "Barber Cuts 2", "packs": ["Barber Cuts 2", "ECFA 2021 (Final Boss Pack)", "ECFA 8 - One Shots", "Girlpocalypse 2023 - Timing", "ITL Online 2023", "RIP 13 Warmup Pack", "RIP 13.5 Girls Singles", "RIP 13.5 Singles", "Tech Spectrum Super"], "steps_type": "dance-single", "subtitle": "", "subtitletranslit": "", "title": "Down The Road", "titletranslit": ""}