{"artist": "N.T.B.-G", "artisttranslit": "", "diff": "Hard", "diff_number": 13, "diffs": ["02fc8f51b0be8289", "2249b65a76fe23ca", "2bdcde3cdc6d1149", "30570fe902b732d9", "368a102c4e5c39b5", "442f7242ecc8a84c", "7aa203c8c8ecd5f5", "8e35d2f2235f3197", "95bff6209a7376b6"], "hash": "2bdcde3cdc6d1149", "pack_name": "Stepmania Revolutionary FIESTA", "packs": ["Stepmania Revolutionary FIESTA"], "steps_type": "dance-double", "subtitle": "", "subtitletranslit": "", "title": "HellFlear(short mix)", "titletranslit": ""}