{"artist": "Dragonforce vs Rhapsody vs DethKlok", "artisttranslit": "", "diff": "Challenge", "diff_number": 18, "diffs": ["1074eb2932a3a609", "603581c22c12eeed", "99b959332085d4c5", "d2f94cb467c7fa3d", "eb42a5c21bb9ce58"], "hash": "99b959332085d4c5", "pack_name": "French Coast Stamina 2 - Complete", "packs": ["French Coast Stamina 2 - Complete", "French Coast Stamina 2 - High Division"], "steps_type": "dance-single", "subtitle": "", "subtitletranslit": "", "title": "[195] Dragonfrance", "titletranslit": ""}