{"artist": "Project B-", "artisttranslit": "", "diff": "Hard", "diff_number": 9, "diffs": ["1809daf5d6f8ca71", "99b9abb0c48ace9c", "b5e6f19d83d95462", "eab43f1b94710b0f"], "hash": "99b9abb0c48ace9c", "pack_name": "Z-I-v Simfile Tournament of Immortals 6", "packs": ["Z-I-v Simfile Tournament of Immortals 6"], "steps_type": "dance-single", "subtitle": "", "subtitletranslit": "", "title": "\u592a\u967dSUNSUN\u30dc\u30f3\u30b8\u30e5\u30fc\u30eb\u30a2\u30d0\u30f3\u30c1\u30e5\u30fc\u30eb", "titletranslit": "Taiyou SUNSUN bonjour aventure"}