{"artist": "\u30ea\u30c4\u30ab / By Yukari-World", "artisttranslit": "Rituka / By Yukari-World", "diff": "Medium", "diff_number": 6, "diffs": ["060fdb546255188e", "1feb6fb74cb1359a", "20f6a45cab1deffe", "33c748b6a6aec14d", "35d95dd330b48e6a", "373ee37c3f6908bc", "8e56936d366aba49", "af74e5244384dac3", "df0801c62fc61d1f", "ff459350fff2a392"], "hash": "20f6a45cab1deffe", "pack_name": "Secret Sister Complex Package", "packs": ["Secret Sister Complex Package"], "steps_type": "dance-single", "subtitle": "Halozy / Starry Presto", "subtitletranslit": "", "title": "\u30b7\u30fc\u30af\u30ec\u30c3\u30c8\u30b7\u30b9\u30bf\u30fc\u30b3\u30f3\u30d7\u30ec\u30c3\u30af\u30b9", "titletranslit": "Secret Sister Complex"}