{"artist": "Melted-noisy-R", "artisttranslit": "Melted-noisy-R", "diff": "Hard", "diff_number": 13, "diffs": ["1cd10817a5dd8617", "2adcec22d759562b", "8fd8dba478c4ea21", "9503b6787429a91f", "bb951fc732452283", "e1242699c400cf0e", "edd44bc1e0c2a931"], "hash": "8fd8dba478c4ea21", "pack_name": "TDR-Mix^2 -Original Edition-", "packs": ["TDR-Mix^2 -Original Edition-"], "steps_type": "dance-double", "subtitle": "", "subtitletranslit": "", "title": "\u307b\u3057\u304f\u305a\u305d\u3089", "titletranslit": "Hoshi Kuzu Sora"}