{"artist": "xi", "artisttranslit": "", "diff": "Hard", "diff_number": 9, "diffs": ["314f45ef704a45b2", "3364a56e07c88f3f", "3cebc693106b8bf6", "4266610d45433eb1", "70a246df9fd184ec", "88127f9225c0a859", "9139ae297aad0625", "e4eada6a4a0e67c9", "ef2d8871ebb3344a", "f1f3771cbc95a6e4"], "hash": "4266610d45433eb1", "pack_name": "DDR Mega-IntegratE Mix 1st Stage", "packs": ["DDR Mega-IntegratE Mix 1st Stage", "Panzer Force 5thmix"], "steps_type": "dance-solo", "subtitle": "", "subtitletranslit": "", "title": "FREEDOM DiVE\u2193", "titletranslit": "FREEDOM DiVE"}