{"directory":"Bad Apple!! (REDALiCE Remix)","title":"Bad Apple!!","artisttranslit":"","subtitletranslit":"","hash":"3b7125865fe378f8","bpms":"0.000=170.000,60.000=85.000,60.500=340.000,61.500=170.000,64.000=85.000,92.000=42.500,93.000=85.000,95.000=170.000,223.000=85.000,253.000=42.500,254.000=170.000","titletranslit":"","artist":"Alstroemeria Records feat. REDALiCE","diff":"Beginner","steps_type":"dance-single","pack_name":"Touhou Pad Pack Rebirth","diff_number":2,"subtitle":"(REDALiCE Remix)"}