{"artist": "NI-NI", "artisttranslit": "", "diff": "Medium", "diff_number": 3, "diffs": ["5edc1998a6df3cd3", "685630b737ba4815", "6bfba5b2434c6a13", "8ae6b7b7d707fb37", "8dada3c6e07804b1", "a6117a80a3912823", "ae817373b83e5a21", "bf2d123be885ef34", "c7d75a3a240a6b04", "c970f88b16f70043", "fc0f33da15c81a00"], "hash": "ae817373b83e5a21", "pack_name": "KoL DDR Before-Max Edit Pack", "packs": ["KoL DDR Before-Max Edit Pack"], "steps_type": "dance-solo", "subtitle": "", "subtitletranslit": "", "title": "1,2,3,4, 007", "titletranslit": ""}