{"artist": "tiger YAMATO", "artisttranslit": "", "diff": "Medium", "diff_number": 6, "diffs": ["05c430a9e6c4db9a", "4387471d242b53f3", "45b9a564bfb96843", "4ff647362fd48fdb", "753020303d4d5f7c", "8260f9a77697f7b2", "95f9ff2c8b8bb254", "d2d918c84fdea91c", "d59e3ae7bdd2250d", "db57e3a192dda683", "ede8c8cd6a1bd9c2", "fe501ef407d37588"], "hash": "d59e3ae7bdd2250d", "pack_name": "KoL DDR Before-Max Edit Pack", "packs": ["DDR 1st Mix to EXTREME", "KoL DDR Before-Max Edit Pack", "Misc DDR"], "steps_type": "dance-single", "subtitle": "", "subtitletranslit": "", "title": "R3", "titletranslit": ""}