{"bpms":"0.000=140.000,28.000=46.667,29.000=420.000,32.000=140.000,76.000=70.000,76.250=210.000,77.000=140.000,140.000=280.000,144.000=140.000,204.000=46.667,205.000=420.000,208.000=140.000","steps_type":"dance-single","title":"Musikk Per Automatikk","pack_name":"Custom 1 - Begin The Fun","directory":"Elliott Berlin - Musikk Per Automatikk","hash":"cc3df979c7e8ad0e","artist":"Elliott Berlin","subtitle":"from Hotline Miami","titletranslit":"","diff_number":8,"subtitletranslit":"","diff":"Challenge","artisttranslit":""}