{"artist": "wrld", "artisttranslit": "", "diff": "Challenge", "diff_number": 11, "diffs": ["15e4aca82204fdbb", "296187093c2c8c3e", "2a849c4401400632", "2ae79705c7cb6a06", "48592cd5c0eceda4", "4af282823af928a2", "6080617acccc0e46", "a3524dcce8b97d3c", "bcc9add41d2a6dd1", "bdee57c2f4743228"], "hash": "bcc9add41d2a6dd1", "pack_name": "Simply Momo Episode 1 (+0.009)", "packs": ["Simply Momo Episode 1 (+0.009)"], "steps_type": "dance-single", "subtitle": "", "subtitletranslit": "", "title": "Triumph", "titletranslit": ""}