{"artist": "4 STRINGS", "artisttranslit": "", "diff": "Easy", "diff_number": 2, "diffs": ["55c5fa169d52822f", "5dff8fccdb2aba96", "6eb7c6bf9a307e4a", "836d864d1bf1dfef", "8c447527ca78f0ee", "8cb36782a69055ed", "cba821da92ac4e12", "e1261a3acb7b862e", "eff2ad04d28b392a"], "hash": "8c447527ca78f0ee", "pack_name": "BarX's Pad Selections", "packs": ["BarX's Pad Selections", "R21Freak And Aaronin.jp Individual Files Pre-2016", "ddr ps2 us"], "steps_type": "dance-double", "subtitle": "(into the night)(radio vocal)", "subtitletranslit": "", "title": "Take Me Away", "titletranslit": ""}