{"artist": "Jirno feat. \u6625\u6b4c\u30ca\u30ca", "artisttranslit": "Jirno feat. Haruka Nana", "diff": "Hard", "diff_number": 11, "diffs": ["24f91efcdd9df96c", "32741a9029f2f61d", "4e8ae88c4b089356", "622c296e1bf670e9", "7689765dd91ed6c4"], "hash": "622c296e1bf670e9", "pack_name": "StepMania - Freedom NANA", "packs": ["StepMania - Freedom NANA"], "steps_type": "dance-single", "subtitle": "", "subtitletranslit": "", "title": "\u30b5\u30de\u30fc\u30ac\u30fc\u30eb\u2606", "titletranslit": "Summer Girl"}