{"artist": "TAMAONSEN feat. Momobako", "artisttranslit": "", "diff": "Medium", "diff_number": 6, "diffs": ["447945756e26a4eb", "4dc146d805d064c0", "55caa3ce9b2b9e94", "6d0689847c2685ec", "8294bc8702e9b458", "8a50186f882aae03", "9c76183b1f37dd3b", "bf3ae1b21d395ed1", "c3b7006457fa0a64"], "hash": "55caa3ce9b2b9e94", "pack_name": "Gensokyo Daydream", "packs": ["Gensokyo Daydream"], "steps_type": "dance-single", "subtitle": "", "subtitletranslit": "", "title": "Figure of Speech", "titletranslit": ""}